tymongo/__init__.py
tymongo/main.py
tymongo/decorators/__init__.py
tymongo/decorators/validate_query_keys.py
tymongo/handler/__init__.py
tymongo/handler/client.py
tymongo-0.0.5.dist-info/LICENSE
tymongo-0.0.5.dist-info/METADATA
tymongo-0.0.5.dist-info/WHEEL
tymongo-0.0.5.dist-info/top_level.txt
tymongo-0.0.5.dist-info/RECORD
