Metadata-Version: 2.1
Name: tymongo
Version: 0.0.5
Summary: A simple MongoDB ORM that support types
Author: Majid Al-Raimi
License: MIT
License-File: LICENSE
Requires-Dist: pymongo
Requires-Dist: pydantic
Requires-Dist: python-dotenv
